yt_yson_bindings/__init__.py
yt_yson_bindings/yson_lib.so
ytsaurus_yson-0.4.10.dist-info/METADATA
ytsaurus_yson-0.4.10.dist-info/WHEEL
ytsaurus_yson-0.4.10.dist-info/top_level.txt
ytsaurus_yson-0.4.10.dist-info/RECORD
